qcclient/__init__.py
qcclient/client.py
qcclient/config.py
qcclient/job.py
qcclient/configs/opt.json
qcclient/configs/pysisyphus_tsopt.yaml
qcclient/configs/rclone.conf
qcclient/configs/sp.json
qcclient_demo-0.3.0.dist-info/METADATA
qcclient_demo-0.3.0.dist-info/WHEEL
qcclient_demo-0.3.0.dist-info/top_level.txt
qcclient_demo-0.3.0.dist-info/RECORD
