Metadata-Version: 2.1
Name: qcclient-demo
Version: 0.3.0
Summary: This is an experimental client for ISTCP 2024
Home-page: 
Author: Xiaojie Wu
Author-email: xiaojie.wu@bytedance.com
Classifier: Programming Language :: Python :: 3
Classifier: License :: OSI Approved :: MIT License
Classifier: Operating System :: OS Independent
Requires-Python: >=3.6
Requires-Dist: boto3
